[
  {
    "keyword": "Feature",
    "name": "NG911 automation sanity",
    "line": 2,
    "id": "ng911-automation-sanity",
    "tags": [
      {
        "name": "@ng911sanity",
        "line": 1
      }
    ],
    "uri": "sanity.feature",
    "elements": [
      {
        "id": "ng911-automation-sanity;login-in-ng911-app-and-validate-home-page",
        "keyword": "Scenario",
        "line": 4,
        "name": "Login in NG911 app and validate home page",
        "tags": [
          {
            "name": "@ng911sanity",
            "line": 1
          }
        ],
        "type": "scenario",
        "steps": [
          {
            "arguments": [],
            "keyword": "Given ",
            "line": 5,
            "name": "I open NG911 login page",
            "result": {
              "status": "passed",
              "duration": 16846000000
            }
          },
          {
            "arguments": [],
            "keyword": "When ",
            "line": 6,
            "name": "I will be on home page",
            "result": {
              "status": "passed",
              "duration": 8544000000
            }
          }
        ]
      },
      {
        "id": "ng911-automation-sanity;validate-psap-page-and-there-apis",
        "keyword": "Scenario",
        "line": 8,
        "name": "validate PSAP page and there APIs",
        "tags": [
          {
            "name": "@ng911sanity",
            "line": 1
          }
        ],
        "type": "scenario",
        "steps": [
          {
            "arguments": [],
            "keyword": "Then ",
            "line": 9,
            "name": "I verify List and Map tab on PSAP page",
            "result": {
              "status": "passed",
              "duration": 10449000000
            }
          },
          {
            "arguments": [],
            "keyword": "And ",
            "line": 10,
            "name": "I verify card details on PSAP page With API",
            "result": {
              "status": "passed",
              "duration": 6504000000
            }
          },
          {
            "arguments": [],
            "keyword": "And ",
            "line": 11,
            "name": "I verify Table Header on PSAP page With API",
            "result": {
              "status": "passed",
              "duration": 14013000000
            }
          }
        ]
      },
      {
        "id": "ng911-automation-sanity;validate-ngcs-page-and-there-apis",
        "keyword": "Scenario",
        "line": 13,
        "name": "validate NGCS page and there APIs",
        "tags": [
          {
            "name": "@ng911sanity",
            "line": 1
          }
        ],
        "type": "scenario",
        "steps": [
          {
            "arguments": [],
            "keyword": "Then ",
            "line": 14,
            "name": "I verify NgcsCore,ComponentStatus and NgcsCoreDevices tab on NGCS page",
            "result": {
              "status": "passed",
              "duration": 4474000000
            }
          },
          {
            "arguments": [],
            "keyword": "And ",
            "line": 15,
            "name": "I verify card details on NGCS page With API",
            "result": {
              "status": "passed",
              "duration": 4186000000
            }
          },
          {
            "arguments": [],
            "keyword": "And ",
            "line": 16,
            "name": "I verify Table Header on NGCS page With API",
            "result": {
              "status": "passed",
              "duration": 2653000000
            }
          }
        ]
      },
      {
        "id": "ng911-automation-sanity;validate-ingress-page-and-there-apis",
        "keyword": "Scenario",
        "line": 18,
        "name": "validate INGRESS page and there APIs",
        "tags": [
          {
            "name": "@ng911sanity",
            "line": 1
          }
        ],
        "type": "scenario",
        "steps": [
          {
            "arguments": [],
            "keyword": "Then ",
            "line": 19,
            "name": "I verify Gateways, SBCs Tabs and data table present on INGRESS page",
            "result": {
              "status": "passed",
              "duration": 5199000000
            }
          },
          {
            "arguments": [],
            "keyword": "And ",
            "line": 20,
            "name": "I verify card details on INGRESS page With API",
            "result": {
              "status": "passed",
              "duration": 3907000000
            }
          },
          {
            "arguments": [],
            "keyword": "And ",
            "line": 21,
            "name": "I verify Table Header on INGRESS page With API",
            "result": {
              "status": "passed",
              "duration": 2829000000
            }
          }
        ]
      },
      {
        "id": "ng911-automation-sanity;validate-alarms-page-and-there-apis",
        "keyword": "Scenario",
        "line": 23,
        "name": "validate ALARMS page and there APIs",
        "tags": [
          {
            "name": "@ng911sanity",
            "line": 1
          }
        ],
        "type": "scenario",
        "steps": [
          {
            "arguments": [],
            "keyword": "Then ",
            "line": 24,
            "name": "I verify data table present on ALARMS page",
            "result": {
              "status": "passed",
              "duration": 5581000000
            }
          },
          {
            "arguments": [],
            "keyword": "And ",
            "line": 25,
            "name": "I verify card details on ALARMS page With API",
            "result": {
              "status": "passed",
              "duration": 7348000000
            }
          },
          {
            "arguments": [],
            "keyword": "And ",
            "line": 26,
            "name": "I verify Table Header on ALARMS page With API",
            "result": {
              "status": "passed",
              "duration": 24221000000
            }
          }
        ]
      }
    ]
  }
]